odoo/addons/stock_warehouse_resupply_route_push/README.rst
odoo/addons/stock_warehouse_resupply_route_push/__init__.py
odoo/addons/stock_warehouse_resupply_route_push/__manifest__.py
odoo/addons/stock_warehouse_resupply_route_push/i18n/it.po
odoo/addons/stock_warehouse_resupply_route_push/i18n/stock_warehouse_resupply_route_push.pot
odoo/addons/stock_warehouse_resupply_route_push/models/__init__.py
odoo/addons/stock_warehouse_resupply_route_push/models/stock_warehouse.py
odoo/addons/stock_warehouse_resupply_route_push/readme/CONFIGURE.md
odoo/addons/stock_warehouse_resupply_route_push/readme/CONTRIBUTORS.md
odoo/addons/stock_warehouse_resupply_route_push/readme/DESCRIPTION.md
odoo/addons/stock_warehouse_resupply_route_push/readme/ROADMAP.md
odoo/addons/stock_warehouse_resupply_route_push/static/description/icon.png
odoo/addons/stock_warehouse_resupply_route_push/static/description/index.html
odoo/addons/stock_warehouse_resupply_route_push/tests/__init__.py
odoo/addons/stock_warehouse_resupply_route_push/tests/test_stock_warehouse_resupply_route_push.py
odoo/addons/stock_warehouse_resupply_route_push/views/stock_warehouse.xml
odoo_addon_stock_warehouse_resupply_route_push-18.0.1.0.0.4.dist-info/METADATA
odoo_addon_stock_warehouse_resupply_route_push-18.0.1.0.0.4.dist-info/WHEEL
odoo_addon_stock_warehouse_resupply_route_push-18.0.1.0.0.4.dist-info/top_level.txt
odoo_addon_stock_warehouse_resupply_route_push-18.0.1.0.0.4.dist-info/RECORD
