Metadata-Version: 2.1
Name: odoo-addon-stock_warehouse_resupply_route_push
Version: 18.0.1.0.0.4
Requires-Python: >=3.10
Requires-Dist: odoo==18.0.*
Summary: Use push rules for resupply from other warehouse routes.
Home-page: https://github.com/OCA/stock-logistics-warehouse
License: LGPL-3
Author: ForgeFlow, Odoo Community Association (OCA)
Author-email: support@odoo-community.org
Classifier: Programming Language :: Python
Classifier: Framework :: Odoo
Classifier: Framework :: Odoo :: 18.0
Classifier: License :: OSI Approved :: GNU Lesser General Public License v3 (LGPLv3)
Classifier: Development Status :: 4 - Beta
